Metadata-Version: 1.2
Name: squabble
Version: 1.3.3
Summary: An extensible linter for SQL
Home-page: https://github.com/erik/squabble
Author: Erik Price
License: GPLv3+
Platform: UNKNOWN
Classifier: Development Status :: 5 - Production/Stable
Classifier: Programming Language :: Python :: 3 :: Only
Classifier: Programming Language :: SQL
Classifier: Topic :: Utilities
Requires-Python: >=3.5
